fds/__init__.py
fds/sdk/__init__.py
fds/sdk/OfficeCloudRefresh/__init__.py
fds/sdk/OfficeCloudRefresh/api_client.py
fds/sdk/OfficeCloudRefresh/configuration.py
fds/sdk/OfficeCloudRefresh/exceptions.py
fds/sdk/OfficeCloudRefresh/model_utils.py
fds/sdk/OfficeCloudRefresh/rest.py
fds/sdk/OfficeCloudRefresh/api/__init__.py
fds/sdk/OfficeCloudRefresh/api/job_management_api.py
fds/sdk/OfficeCloudRefresh/api/refresh_operations_api.py
fds/sdk/OfficeCloudRefresh/apis/__init__.py
fds/sdk/OfficeCloudRefresh/model/__init__.py
fds/sdk/OfficeCloudRefresh/model/active_job_status.py
fds/sdk/OfficeCloudRefresh/model/active_job_status_list.py
fds/sdk/OfficeCloudRefresh/model/error.py
fds/sdk/OfficeCloudRefresh/model/error_code.py
fds/sdk/OfficeCloudRefresh/model/errors.py
fds/sdk/OfficeCloudRefresh/model/file_group_info.py
fds/sdk/OfficeCloudRefresh/model/file_group_info_data.py
fds/sdk/OfficeCloudRefresh/model/job_status.py
fds/sdk/OfficeCloudRefresh/model/job_status_data.py
fds/sdk/OfficeCloudRefresh/models/__init__.py
fds_sdk_officecloudrefresh-0.2.1.dist-info/licenses/LICENSE
fds_sdk_officecloudrefresh-0.2.1.dist-info/METADATA
fds_sdk_officecloudrefresh-0.2.1.dist-info/WHEEL
fds_sdk_officecloudrefresh-0.2.1.dist-info/top_level.txt
fds_sdk_officecloudrefresh-0.2.1.dist-info/RECORD
